setup.cfg
setup.py
openscratch.egg-info/PKG-INFO
openscratch.egg-info/SOURCES.txt
openscratch.egg-info/dependency_links.txt
openscratch.egg-info/top_level.txt
ywdblogmath/__init__.py
ywdblogmath/add.py
ywdblogmath/division.py
ywdblogmath/multiply.py
ywdblogmath/subtract.py
ywdblogmath/adv/__init__.py
ywdblogmath/adv/sqrt.py