Metadata-Version: 1.0
Name: openscratch
Version: 0.1
Summary: openscratch
Home-page: http://www.openscratch.com/
Author: shaolizhi
Author-email: 53733522@qq.com
License: UNKNOWN
Platform: UNKNOWN
